fast_scaffold/__init__.py
fast_scaffold/cli.py
fast_scaffold/commands/__init__.py
fast_scaffold/commands/project.py
fast_scaffold/generator.py
fast_scaffold/templates/project/README.md.mako
fast_scaffold/templates/project/app/__init__.py.mako
fast_scaffold/templates/project/app/main.py.mako
fast_scaffold/templates/project/pyproject.toml.mako
fast_scaffold/templates/project/tests/__init__.py.mako
fast_scaffold-0.1.1.dist-info/METADATA
fast_scaffold-0.1.1.dist-info/WHEEL
fast_scaffold-0.1.1.dist-info/entry_points.txt
fast_scaffold-0.1.1.dist-info/RECORD
