Metadata-Version: 2.4
Name: fast-scaffold
Version: 0.1.1
Summary: CLI para gerar scaffolding de projetos FastAPI
Author: Ramon Willer
Author-email: willer.ramon@gmail.com
Requires-Python: >=3.10
Classifier: Programming Language :: Python :: 3
Classifier: Programming Language :: Python :: 3.10
Classifier: Programming Language :: Python :: 3.11
Classifier: Programming Language :: Python :: 3.12
Classifier: Programming Language :: Python :: 3.13
Classifier: Programming Language :: Python :: 3.14
Requires-Dist: mako (>=1.3.10,<2.0.0)
Requires-Dist: typer (>=0.21.1,<0.22.0)
